[
  {
    "customerId": "TFRHY-0",
    "departmentId": "DEPTXE-0ER",
    "name": "GFTH",
    "email": "example@gmail.com",
    "tms": "23 GB"
  },
  {
    "customerId": "TFRHY-1",
    "departmentId": "DEPTXE-1ER",
    "name": "GFTH",
    "email": "example@gmail.com",
    "tms": "23 GB"
  },
  {
    "customerId": "TFRHY-2",
    "departmentId": "DEPTXE-2ER",
    "name": "GFTH",
    "email": "example@gmail.com",
    "tms": "23 GB"
  },
  {
    "customerId": "TFRHY-3",
    "departmentId": "DEPTXE-3ER",
    "name": "GFTH",
    "email": "example@gmail.com",
    "tms": "23 GB"
  },
  {
    "customerId": "TFRHY-4",
    "departmentId": "DEPTXE-4ER",
    "name": "GFTH",
    "email": "example@gmail.com",
    "tms": "23 GB"
  },
  {
    "customerId": "TFRHY-5",
    "departmentId": "DEPTXE-5ER",
    "name": "GFTH",
    "email": "example@gmail.com",
    "tms": "23 GB"
  },
  {
    "customerId": "TFRHY-6",
    "departmentId": "DEPTXE-6ER",
    "name": "GFTH",
    "email": "example@gmail.com",
    "tms": "23 GB"
  },
  {
    "customerId": "TFRHY-7",
    "departmentId": "DEPTXE-7ER",
    "name": "GFTH",
    "email": "example@gmail.com",
    "tms": "23 GB"
  },
  {
    "customerId": "TFRHY-8",
    "departmentId": "DEPTXE-8ER",
    "name": "GFTH",
    "email": "example@gmail.com",
    "tms": "23 GB"
  },
  {
    "customerId": "TFRHY-9",
    "departmentId": "DEPTXE-9ER",
    "name": "GFTH",
    "email": "example@gmail.com",
    "tms": "23 GB"
  },
  {
    "customerId": "TFRHY-10",
    "departmentId": "DEPTXE-10ER",
    "name": "GFTH",
    "email": "example@gmail.com",
    "tms": "23 GB"
  },
  {
    "customerId": "TFRHY-11",
    "departmentId": "DEPTXE-11ER",
    "name": "GFTH",
    "email": "example@gmail.com",
    "tms": "23 GB"
  },
  {
    "customerId": "TFRHY-12",
    "departmentId": "DEPTXE-12ER",
    "name": "GFTH",
    "email": "example@gmail.com",
    "tms": "23 GB"
  },
  {
    "customerId": "TFRHY-13",
    "departmentId": "DEPTXE-13ER",
    "name": "GFTH",
    "email": "example@gmail.com",
    "tms": "23 GB"
  },
  {
    "customerId": "TFRHY-14",
    "departmentId": "DEPTXE-14ER",
    "name": "GFTH",
    "email": "example@gmail.com",
    "tms": "23 GB"
  },
  {
    "customerId": "TFRHY-15",
    "departmentId": "DEPTXE-15ER",
    "name": "GFTH",
    "email": "example@gmail.com",
    "tms": "23 GB"
  },
  {
    "customerId": "TFRHY-16",
    "departmentId": "DEPTXE-16ER",
    "name": "GFTH",
    "email": "example@gmail.com",
    "tms": "23 GB"
  },
  {
    "customerId": "TFRHY-17",
    "departmentId": "DEPTXE-17ER",
    "name": "GFTH",
    "email": "example@gmail.com",
    "tms": "23 GB"
  },
  {
    "customerId": "TFRHY-18",
    "departmentId": "DEPTXE-18ER",
    "name": "GFTH",
    "email": "example@gmail.com",
    "tms": "23 GB"
  },
  {
    "customerId": "TFRHY-19",
    "departmentId": "DEPTXE-19ER",
    "name": "GFTH",
    "email": "example@gmail.com",
    "tms": "23 GB"
  },
  {
    "customerId": "TFRHY-20",
    "departmentId": "DEPTXE-20ER",
    "name": "GFTH",
    "email": "example@gmail.com",
    "tms": "23 GB"
  },
  {
    "customerId": "TFRHY-21",
    "departmentId": "DEPTXE-21ER",
    "name": "GFTH",
    "email": "example@gmail.com",
    "tms": "23 GB"
  },
  {
    "customerId": "TFRHY-22",
    "departmentId": "DEPTXE-22ER",
    "name": "GFTH",
    "email": "example@gmail.com",
    "tms": "23 GB"
  },
  {
    "customerId": "TFRHY-23",
    "departmentId": "DEPTXE-23ER",
    "name": "GFTH",
    "email": "example@gmail.com",
    "tms": "23 GB"
  },
  {
    "customerId": "TFRHY-24",
    "departmentId": "DEPTXE-24ER",
    "name": "GFTH",
    "email": "example@gmail.com",
    "tms": "23 GB"
  },
  {
    "customerId": "TFRHY-25",
    "departmentId": "DEPTXE-25ER",
    "name": "GFTH",
    "email": "example@gmail.com",
    "tms": "23 GB"
  },
  {
    "customerId": "TFRHY-26",
    "departmentId": "DEPTXE-26ER",
    "name": "GFTH",
    "email": "example@gmail.com",
    "tms": "23 GB"
  },
  {
    "customerId": "TFRHY-27",
    "departmentId": "DEPTXE-27ER",
    "name": "GFTH",
    "email": "example@gmail.com",
    "tms": "23 GB"
  },
  {
    "customerId": "TFRHY-28",
    "departmentId": "DEPTXE-28ER",
    "name": "GFTH",
    "email": "example@gmail.com",
    "tms": "23 GB"
  },
  {
    "customerId": "TFRHY-29",
    "departmentId": "DEPTXE-29ER",
    "name": "GFTH",
    "email": "example@gmail.com",
    "tms": "23 GB"
  },
  {
    "customerId": "TFRHY-30",
    "departmentId": "DEPTXE-30ER",
    "name": "GFTH",
    "email": "example@gmail.com",
    "tms": "23 GB"
  },
  {
    "customerId": "TFRHY-31",
    "departmentId": "DEPTXE-31ER",
    "name": "GFTH",
    "email": "example@gmail.com",
    "tms": "23 GB"
  },
  {
    "customerId": "TFRHY-32",
    "departmentId": "DEPTXE-32ER",
    "name": "GFTH",
    "email": "example@gmail.com",
    "tms": "23 GB"
  },
  {
    "customerId": "TFRHY-33",
    "departmentId": "DEPTXE-33ER",
    "name": "GFTH",
    "email": "example@gmail.com",
    "tms": "23 GB"
  },
  {
    "customerId": "TFRHY-34",
    "departmentId": "DEPTXE-34ER",
    "name": "GFTH",
    "email": "example@gmail.com",
    "tms": "23 GB"
  },
  {
    "customerId": "TFRHY-35",
    "departmentId": "DEPTXE-35ER",
    "name": "GFTH",
    "email": "example@gmail.com",
    "tms": "23 GB"
  },
  {
    "customerId": "TFRHY-36",
    "departmentId": "DEPTXE-36ER",
    "name": "GFTH",
    "email": "example@gmail.com",
    "tms": "23 GB"
  },
  {
    "customerId": "TFRHY-37",
    "departmentId": "DEPTXE-37ER",
    "name": "GFTH",
    "email": "example@gmail.com",
    "tms": "23 GB"
  },
  {
    "customerId": "TFRHY-38",
    "departmentId": "DEPTXE-38ER",
    "name": "GFTH",
    "email": "example@gmail.com",
    "tms": "23 GB"
  },
  {
    "customerId": "TFRHY-39",
    "departmentId": "DEPTXE-39ER",
    "name": "GFTH",
    "email": "example@gmail.com",
    "tms": "23 GB"
  },
  {
    "customerId": "TFRHY-40",
    "departmentId": "DEPTXE-40ER",
    "name": "GFTH",
    "email": "example@gmail.com",
    "tms": "23 GB"
  },
  {
    "customerId": "TFRHY-41",
    "departmentId": "DEPTXE-41ER",
    "name": "GFTH",
    "email": "example@gmail.com",
    "tms": "23 GB"
  },
  {
    "customerId": "TFRHY-42",
    "departmentId": "DEPTXE-42ER",
    "name": "GFTH",
    "email": "example@gmail.com",
    "tms": "23 GB"
  },
  {
    "customerId": "TFRHY-43",
    "departmentId": "DEPTXE-43ER",
    "name": "GFTH",
    "email": "example@gmail.com",
    "tms": "23 GB"
  },
  {
    "customerId": "TFRHY-44",
    "departmentId": "DEPTXE-44ER",
    "name": "GFTH",
    "email": "example@gmail.com",
    "tms": "23 GB"
  },
  {
    "customerId": "TFRHY-45",
    "departmentId": "DEPTXE-45ER",
    "name": "GFTH",
    "email": "example@gmail.com",
    "tms": "23 GB"
  },
  {
    "customerId": "TFRHY-46",
    "departmentId": "DEPTXE-46ER",
    "name": "GFTH",
    "email": "example@gmail.com",
    "tms": "23 GB"
  },
  {
    "customerId": "TFRHY-47",
    "departmentId": "DEPTXE-47ER",
    "name": "GFTH",
    "email": "example@gmail.com",
    "tms": "23 GB"
  },
  {
    "customerId": "TFRHY-48",
    "departmentId": "DEPTXE-48ER",
    "name": "GFTH",
    "email": "example@gmail.com",
    "tms": "23 GB"
  },
  {
    "customerId": "TFRHY-49",
    "departmentId": "DEPTXE-49ER",
    "name": "GFTH",
    "email": "example@gmail.com",
    "tms": "23 GB"
  }
]